{
  "_nota": "🏆 16avos definidos — todos los grupos jugados, terceros incluidos",
  "_stats": {
    "A": {
      "🇲🇽 MÉXICO": {
        "pts": 6,
        "gf": 3,
        "ga": 0
      },
      "🇰🇷 COREA DEL SUR": {
        "pts": 3,
        "gf": 2,
        "ga": 2
      },
      "🇨🇿 REP. CHECA": {
        "pts": 1,
        "gf": 1,
        "ga": 2
      },
      "🇿🇦 SUDÁFRICA": {
        "pts": 1,
        "gf": 0,
        "ga": 2
      }
    },
    "B": {
      "🇨🇦 CANADÁ": {
        "pts": 4,
        "gf": 7,
        "ga": 1
      },
      "🇨🇭 SUIZA": {
        "pts": 4,
        "gf": 4,
        "ga": 1
      },
      "🇧🇦 BOSNIA Y HERZEGOVINA": {
        "pts": 1,
        "gf": 1,
        "ga": 4
      },
      "🇶🇦 QATAR": {
        "pts": 1,
        "gf": 1,
        "ga": 7
      }
    },
    "C": {
      "🇧🇷 BRASIL": {
        "pts": 4,
        "gf": 4,
        "ga": 1
      },
      "🇲🇦 MARRUECOS": {
        "pts": 4,
        "gf": 2,
        "ga": 1
      },
      "🏴󠁧󠁢󠁳󠁣󠁴󠁿 ESCOCIA": {
        "pts": 3,
        "gf": 1,
        "ga": 1
      },
      "🇭🇹 HAITÍ": {
        "pts": 0,
        "gf": 0,
        "ga": 4
      }
    },
    "D": {
      "🇺🇸 ESTADOS UNIDOS": {
        "pts": 6,
        "gf": 6,
        "ga": 1
      },
      "🇦🇺 AUSTRALIA": {
        "pts": 3,
        "gf": 2,
        "ga": 2
      },
      "🇵🇾 PARAGUAY": {
        "pts": 3,
        "gf": 2,
        "ga": 4
      },
      "🇹🇷 TURQUÍA": {
        "pts": 0,
        "gf": 1,
        "ga": 4
      }
    },
    "E": {
      "🇩🇪 ALEMANIA": {
        "pts": 6,
        "gf": 8,
        "ga": 1
      },
      "🇨🇮 COSTA DE MARFIL": {
        "pts": 3,
        "gf": 1,
        "ga": 1
      },
      "🇪🇨 ECUADOR": {
        "pts": 1,
        "gf": 1,
        "ga": 2
      },
      "CURAÇAO": {
        "pts": 1,
        "gf": 1,
        "ga": 7
      }
    },
    "F": {
      "🇳🇱 HOLANDA": {
        "pts": 4,
        "gf": 5,
        "ga": 1
      },
      "🇸🇪 SUECIA": {
        "pts": 3,
        "gf": 3,
        "ga": 3
      },
      "🇯🇵 JAPÓN": {
        "pts": 1,
        "gf": 2,
        "ga": 2
      },
      "🇹🇳 TÚNEZ": {
        "pts": 0,
        "gf": 1,
        "ga": 5
      }
    },
    "G": {
      "🇳🇿 NUEVA ZELANDA": {
        "pts": 1,
        "gf": 2,
        "ga": 2
      },
      "🇮🇷 IRÁN": {
        "pts": 1,
        "gf": 2,
        "ga": 2
      },
      "🇧🇪 BÉLGICA": {
        "pts": 1,
        "gf": 1,
        "ga": 1
      },
      "🇪🇬 EGIPTO": {
        "pts": 1,
        "gf": 1,
        "ga": 1
      }
    },
    "H": {
      "🇺🇾 URUGUAY": {
        "pts": 1,
        "gf": 1,
        "ga": 1
      },
      "🇸🇦 ARABIA SAUDÍ": {
        "pts": 1,
        "gf": 1,
        "ga": 1
      },
      "🇪🇸 ESPAÑA": {
        "pts": 1,
        "gf": 0,
        "ga": 0
      },
      "🇨🇻 CABO VERDE": {
        "pts": 1,
        "gf": 0,
        "ga": 0
      }
    },
    "I": {
      "🇳🇴 NORUEGA": {
        "pts": 3,
        "gf": 3,
        "ga": 0
      },
      "🇫🇷 FRANCIA": {
        "pts": 3,
        "gf": 2,
        "ga": 0
      },
      "🇸🇳 SENEGAL": {
        "pts": 0,
        "gf": 0,
        "ga": 2
      },
      "🇮🇶 IRAK": {
        "pts": 0,
        "gf": 0,
        "ga": 3
      }
    },
    "J": {
      "🇦🇷 ARGENTINA": {
        "pts": 3,
        "gf": 3,
        "ga": 0
      },
      "🇦🇹 AUSTRIA": {
        "pts": 3,
        "gf": 2,
        "ga": 0
      },
      "🇯🇴 JORDANIA": {
        "pts": 0,
        "gf": 0,
        "ga": 2
      },
      "🇩🇿 ARGELIA": {
        "pts": 0,
        "gf": 0,
        "ga": 3
      }
    },
    "K": {
      "🇨🇴 COLOMBIA": {
        "pts": 3,
        "gf": 2,
        "ga": 0
      },
      "🇨🇩 REP. CONGO": {
        "pts": 1,
        "gf": 0,
        "ga": 0
      },
      "🇵🇹 PORTUGAL": {
        "pts": 1,
        "gf": 1,
        "ga": 1
      },
      "🇺🇿 UZBEKISTÁN": {
        "pts": 0,
        "gf": 0,
        "ga": 2
      }
    },
    "L": {
      "🇬🇧 INGLATERRA": {
        "pts": 3,
        "gf": 2,
        "ga": 0
      },
      "🇬🇭 GHANA": {
        "pts": 3,
        "gf": 1,
        "ga": 0
      },
      "🇵🇦 PANAMÁ": {
        "pts": 0,
        "gf": 0,
        "ga": 1
      },
      "🇭🇷 CROACIA": {
        "pts": 0,
        "gf": 0,
        "ga": 2
      }
    }
  },
  "grupos": {
    "A": {
      "🇲🇽 MÉXICO": 1,
      "🇰🇷 COREA DEL SUR": 2,
      "🇨🇿 REP. CHECA": 3,
      "🇿🇦 SUDÁFRICA": 4
    },
    "B": {
      "🇨🇦 CANADÁ": 1,
      "🇨🇭 SUIZA": 2,
      "🇧🇦 BOSNIA Y HERZEGOVINA": 3,
      "🇶🇦 QATAR": 4
    },
    "C": {
      "🇧🇷 BRASIL": 1,
      "🇲🇦 MARRUECOS": 2,
      "🏴󠁧󠁢󠁳󠁣󠁴󠁿 ESCOCIA": 3,
      "🇭🇹 HAITÍ": 4
    },
    "D": {
      "🇺🇸 ESTADOS UNIDOS": 1,
      "🇦🇺 AUSTRALIA": 2,
      "🇵🇾 PARAGUAY": 3,
      "🇹🇷 TURQUÍA": 4
    },
    "E": {
      "🇩🇪 ALEMANIA": 1,
      "🇨🇮 COSTA DE MARFIL": 2,
      "🇪🇨 ECUADOR": 3,
      "CURAÇAO": 4
    },
    "F": {
      "🇳🇱 HOLANDA": 1,
      "🇸🇪 SUECIA": 2,
      "🇯🇵 JAPÓN": 3,
      "🇹🇳 TÚNEZ": 4
    },
    "G": {
      "🇳🇿 NUEVA ZELANDA": 1,
      "🇮🇷 IRÁN": 2,
      "🇧🇪 BÉLGICA": 3,
      "🇪🇬 EGIPTO": 4
    },
    "H": {
      "🇺🇾 URUGUAY": 1,
      "🇸🇦 ARABIA SAUDÍ": 2,
      "🇪🇸 ESPAÑA": 3,
      "🇨🇻 CABO VERDE": 4
    },
    "I": {
      "🇳🇴 NORUEGA": 1,
      "🇫🇷 FRANCIA": 2,
      "🇸🇳 SENEGAL": 3,
      "🇮🇶 IRAK": 4
    },
    "J": {
      "🇦🇷 ARGENTINA": 1,
      "🇦🇹 AUSTRIA": 2,
      "🇯🇴 JORDANIA": 3,
      "🇩🇿 ARGELIA": 4
    },
    "K": {
      "🇨🇴 COLOMBIA": 1,
      "🇨🇩 REP. CONGO": 2,
      "🇵🇹 PORTUGAL": 3,
      "🇺🇿 UZBEKISTÁN": 4
    },
    "L": {
      "🇬🇧 INGLATERRA": 1,
      "🇬🇭 GHANA": 2,
      "🇵🇦 PANAMÁ": 3,
      "🇭🇷 CROACIA": 4
    }
  },
  "ronda_16avos": [
    {
      "slot": "1E",
      "equipo": "🇩🇪 ALEMANIA"
    },
    {
      "slot": "3 ABCDF",
      "equipo": "🏴󠁧󠁢󠁳󠁣󠁴󠁿 ESCOCIA"
    },
    {
      "slot": "1I",
      "equipo": "🇳🇴 NORUEGA"
    },
    {
      "slot": "3 CDFGH",
      "equipo": "🇵🇾 PARAGUAY"
    },
    {
      "slot": "2A",
      "equipo": "🇰🇷 COREA DEL SUR"
    },
    {
      "slot": "2B",
      "equipo": "🇨🇭 SUIZA"
    },
    {
      "slot": "1F",
      "equipo": "🇳🇱 HOLANDA"
    },
    {
      "slot": "2C",
      "equipo": "🇲🇦 MARRUECOS"
    },
    {
      "slot": "2K",
      "equipo": "🇨🇩 REP. CONGO"
    },
    {
      "slot": "2L",
      "equipo": "🇬🇭 GHANA"
    },
    {
      "slot": "1H",
      "equipo": "🇺🇾 URUGUAY"
    },
    {
      "slot": "2J",
      "equipo": "🇦🇹 AUSTRIA"
    },
    {
      "slot": "1D",
      "equipo": "🇺🇸 ESTADOS UNIDOS"
    },
    {
      "slot": "3 BEFIJ",
      "equipo": "🇯🇵 JAPÓN"
    },
    {
      "slot": "1G",
      "equipo": "🇳🇿 NUEVA ZELANDA"
    },
    {
      "slot": "3 AEFHIJ",
      "equipo": "🇨🇿 REP. CHECA"
    },
    {
      "slot": "1C",
      "equipo": "🇧🇷 BRASIL"
    },
    {
      "slot": "2F",
      "equipo": "🇸🇪 SUECIA"
    },
    {
      "slot": "2E",
      "equipo": "🇨🇮 COSTA DE MARFIL"
    },
    {
      "slot": "2I",
      "equipo": "🇫🇷 FRANCIA"
    },
    {
      "slot": "1A",
      "equipo": "🇲🇽 MÉXICO"
    },
    {
      "slot": "3 CEFHI",
      "equipo": "🇪🇸 ESPAÑA"
    },
    {
      "slot": "1L",
      "equipo": "🇬🇧 INGLATERRA"
    },
    {
      "slot": "3 EHIJK",
      "equipo": "🇵🇹 PORTUGAL"
    },
    {
      "slot": "1J",
      "equipo": "🇦🇷 ARGENTINA"
    },
    {
      "slot": "2H",
      "equipo": "🇸🇦 ARABIA SAUDÍ"
    },
    {
      "slot": "2D",
      "equipo": "🇦🇺 AUSTRALIA"
    },
    {
      "slot": "2G",
      "equipo": "🇮🇷 IRÁN"
    },
    {
      "slot": "1B",
      "equipo": "🇨🇦 CANADÁ"
    },
    {
      "slot": "3 EFGIJ",
      "equipo": "🇧🇪 BÉLGICA"
    },
    {
      "slot": "1K",
      "equipo": "🇨🇴 COLOMBIA"
    },
    {
      "slot": "3 DEIJL",
      "equipo": "🇪🇨 ECUADOR"
    }
  ],
  "ronda_8avos": [],
  "ronda_cuartos": [],
  "ronda_semifinales": [],
  "finales": {
    "campeon": "",
    "segundo": "",
    "tercero": "",
    "cuarto": ""
  }
}