{
  "_nota": "Datos desde worldcup26.ir вЂ” 8/32 equipos en 16avos",
  "_stats": {
    "A": {
      "рџ‡Ірџ‡Ѕ MГ‰XICO": {
        "pts": 3,
        "gf": 2,
        "ga": 0
      },
      "рџ‡їрџ‡¦ SUDГЃFRICA": {
        "pts": 0,
        "gf": 0,
        "ga": 2
      },
      "рџ‡°рџ‡· COREA DEL SUR": {
        "pts": 3,
        "gf": 2,
        "ga": 1
      },
      "рџ‡Ёрџ‡ї REP. CHECA": {
        "pts": 0,
        "gf": 1,
        "ga": 2
      }
    },
    "B": {
      "рџ‡Ёрџ‡¦ CANADГЃ": {
        "pts": 1,
        "gf": 1,
        "ga": 1
      },
      "рџ‡§рџ‡¦ BOSNIA Y HERZEGOVINA": {
        "pts": 1,
        "gf": 1,
        "ga": 1
      },
      "рџ‡¶рџ‡¦ QATAR": {
        "pts": 1,
        "gf": 1,
        "ga": 1
      },
      "рџ‡Ёрџ‡­ SUIZA": {
        "pts": 1,
        "gf": 1,
        "ga": 1
      }
    },
    "D": {
      "рџ‡єрџ‡ё ESTADOS UNIDOS": {
        "pts": 3,
        "gf": 4,
        "ga": 1
      },
      "рџ‡µрџ‡ѕ PARAGUAY": {
        "pts": 0,
        "gf": 1,
        "ga": 4
      },
      "рџ‡¦рџ‡є AUSTRALIA": {
        "pts": 3,
        "gf": 2,
        "ga": 0
      },
      "рџ‡№рџ‡· TURQUГЌA": {
        "pts": 0,
        "gf": 0,
        "ga": 2
      }
    },
    "C": {
      "рџ‡­рџ‡№ HAITГЌ": {
        "pts": 0,
        "gf": 0,
        "ga": 1
      },
      "рџЏґу Ѓ§у Ѓўу Ѓіу ЃЈу Ѓґу Ѓї ESCOCIA": {
        "pts": 3,
        "gf": 1,
        "ga": 0
      },
      "рџ‡§рџ‡· BRASIL": {
        "pts": 1,
        "gf": 1,
        "ga": 1
      },
      "рџ‡Ірџ‡¦ MARRUECOS": {
        "pts": 1,
        "gf": 1,
        "ga": 1
      }
    },
    "E": {
      "рџ‡Єрџ‡Ё ECUADOR": {
        "pts": 0,
        "gf": 0,
        "ga": 0
      },
      "рџ‡©рџ‡Є ALEMANIA": {
        "pts": 0,
        "gf": 0,
        "ga": 0
      },
      "рџ‡Ёрџ‡® COSTA DE MARFIL": {
        "pts": 0,
        "gf": 0,
        "ga": 0
      },
      "CURAГ‡AO": {
        "pts": 0,
        "gf": 0,
        "ga": 0
      }
    },
    "F": {
      "рџ‡Їрџ‡µ JAPГ“N": {
        "pts": 0,
        "gf": 0,
        "ga": 0
      },
      "рџ‡ірџ‡± HOLANDA": {
        "pts": 0,
        "gf": 0,
        "ga": 0
      },
      "рџ‡№рџ‡і TГљNEZ": {
        "pts": 0,
        "gf": 0,
        "ga": 0
      },
      "рџ‡ёрџ‡Є SUECIA": {
        "pts": 0,
        "gf": 0,
        "ga": 0
      }
    },
    "G": {
      "рџ‡ірџ‡ї NUEVA ZELANDA": {
        "pts": 0,
        "gf": 0,
        "ga": 0
      },
      "рџ‡§рџ‡Є BГ‰LGICA": {
        "pts": 0,
        "gf": 0,
        "ga": 0
      },
      "рџ‡Єрџ‡¬ EGIPTO": {
        "pts": 0,
        "gf": 0,
        "ga": 0
      },
      "рџ‡®рџ‡· IRГЃN": {
        "pts": 0,
        "gf": 0,
        "ga": 0
      }
    },
    "H": {
      "рџ‡Єрџ‡ё ESPAГ‘A": {
        "pts": 0,
        "gf": 0,
        "ga": 0
      },
      "рџ‡єрџ‡ѕ URUGUAY": {
        "pts": 0,
        "gf": 0,
        "ga": 0
      },
      "рџ‡ёрџ‡¦ ARABIA SAUDГЌ": {
        "pts": 0,
        "gf": 0,
        "ga": 0
      },
      "рџ‡Ёрџ‡» CABO VERDE": {
        "pts": 0,
        "gf": 0,
        "ga": 0
      }
    },
    "I": {
      "рџ‡®рџ‡¶ IRAK": {
        "pts": 0,
        "gf": 0,
        "ga": 0
      },
      "рџ‡«рџ‡· FRANCIA": {
        "pts": 0,
        "gf": 0,
        "ga": 0
      },
      "рџ‡ірџ‡ґ NORUEGA": {
        "pts": 0,
        "gf": 0,
        "ga": 0
      },
      "рџ‡ёрџ‡і SENEGAL": {
        "pts": 0,
        "gf": 0,
        "ga": 0
      }
    },
    "J": {
      "рџ‡©рџ‡ї ARGELIA": {
        "pts": 0,
        "gf": 0,
        "ga": 0
      },
      "рџ‡¦рџ‡· ARGENTINA": {
        "pts": 0,
        "gf": 0,
        "ga": 0
      },
      "рџ‡¦рџ‡№ AUSTRIA": {
        "pts": 0,
        "gf": 0,
        "ga": 0
      },
      "рџ‡Їрџ‡ґ JORDANIA": {
        "pts": 0,
        "gf": 0,
        "ga": 0
      }
    },
    "K": {
      "DEMOCRATIC REPUBLIC OF THE CONGO": {
        "pts": 0,
        "gf": 0,
        "ga": 0
      },
      "рџ‡єрџ‡ї UZBEKISTГЃN": {
        "pts": 0,
        "gf": 0,
        "ga": 0
      },
      "рџ‡Ёрџ‡ґ COLOMBIA": {
        "pts": 0,
        "gf": 0,
        "ga": 0
      },
      "рџ‡µрџ‡№ PORTUGAL": {
        "pts": 0,
        "gf": 0,
        "ga": 0
      }
    },
    "L": {
      "рџ‡¬рџ‡§ INGLATERRA": {
        "pts": 0,
        "gf": 0,
        "ga": 0
      },
      "рџ‡­рџ‡· CROACIA": {
        "pts": 0,
        "gf": 0,
        "ga": 0
      },
      "рџ‡µрџ‡¦ PANAMГЃ": {
        "pts": 0,
        "gf": 0,
        "ga": 0
      },
      "рџ‡¬рџ‡­ GHANA": {
        "pts": 0,
        "gf": 0,
        "ga": 0
      }
    }
  },
  "grupos": {
    "A": {
      "рџ‡Ірџ‡Ѕ MГ‰XICO": 1,
      "рџ‡°рџ‡· COREA DEL SUR": 2,
      "рџ‡Ёрџ‡ї REP. CHECA": 3,
      "рџ‡їрџ‡¦ SUDГЃFRICA": 4
    },
    "B": {
      "рџ‡¶рџ‡¦ QATAR": 1,
      "рџ‡Ёрџ‡¦ CANADГЃ": 2,
      "рџ‡Ёрџ‡­ SUIZA": 3,
      "рџ‡§рџ‡¦ BOSNIA Y HERZEGOVINA": 4
    },
    "D": {
      "рџ‡єрџ‡ё ESTADOS UNIDOS": 1,
      "рџ‡¦рџ‡є AUSTRALIA": 2,
      "рџ‡№рџ‡· TURQUГЌA": 3,
      "рџ‡µрџ‡ѕ PARAGUAY": 4
    },
    "C": {
      "рџЏґу Ѓ§у Ѓўу Ѓіу ЃЈу Ѓґу Ѓї ESCOCIA": 1,
      "рџ‡Ірџ‡¦ MARRUECOS": 2,
      "рџ‡§рџ‡· BRASIL": 3,
      "рџ‡­рџ‡№ HAITГЌ": 4
    },
    "E": {
      "рџ‡Єрџ‡Ё ECUADOR": 0,
      "рџ‡©рџ‡Є ALEMANIA": 0,
      "рџ‡Ёрџ‡® COSTA DE MARFIL": 0,
      "CURAГ‡AO": 0
    },
    "F": {
      "рџ‡Їрџ‡µ JAPГ“N": 0,
      "рџ‡ірџ‡± HOLANDA": 0,
      "рџ‡№рџ‡і TГљNEZ": 0,
      "рџ‡ёрџ‡Є SUECIA": 0
    },
    "G": {
      "рџ‡ірџ‡ї NUEVA ZELANDA": 0,
      "рџ‡§рџ‡Є BГ‰LGICA": 0,
      "рџ‡Єрџ‡¬ EGIPTO": 0,
      "рџ‡®рџ‡· IRГЃN": 0
    },
    "H": {
      "рџ‡Єрџ‡ё ESPAГ‘A": 0,
      "рџ‡єрџ‡ѕ URUGUAY": 0,
      "рџ‡ёрџ‡¦ ARABIA SAUDГЌ": 0,
      "рџ‡Ёрџ‡» CABO VERDE": 0
    },
    "I": {
      "рџ‡®рџ‡¶ IRAK": 0,
      "рџ‡«рџ‡· FRANCIA": 0,
      "рџ‡ірџ‡ґ NORUEGA": 0,
      "рџ‡ёрџ‡і SENEGAL": 0
    },
    "J": {
      "рџ‡©рџ‡ї ARGELIA": 0,
      "рџ‡¦рџ‡· ARGENTINA": 0,
      "рџ‡¦рџ‡№ AUSTRIA": 0,
      "рџ‡Їрџ‡ґ JORDANIA": 0
    },
    "K": {
      "DEMOCRATIC REPUBLIC OF THE CONGO": 0,
      "рџ‡єрџ‡ї UZBEKISTГЃN": 0,
      "рџ‡Ёрџ‡ґ COLOMBIA": 0,
      "рџ‡µрџ‡№ PORTUGAL": 0
    },
    "L": {
      "рџ‡¬рџ‡§ INGLATERRA": 0,
      "рџ‡­рџ‡· CROACIA": 0,
      "рџ‡µрџ‡¦ PANAMГЃ": 0,
      "рџ‡¬рџ‡­ GHANA": 0
    }
  },
  "ronda_16avos": [
    {
      "slot": "1E",
      "equipo": ""
    },
    {
      "slot": "3 ABCDF",
      "equipo": ""
    },
    {
      "slot": "1I",
      "equipo": ""
    },
    {
      "slot": "3 CDFGH",
      "equipo": ""
    },
    {
      "slot": "2A",
      "equipo": "рџ‡°рџ‡· COREA DEL SUR"
    },
    {
      "slot": "2B",
      "equipo": "рџ‡Ёрџ‡¦ CANADГЃ"
    },
    {
      "slot": "1F",
      "equipo": ""
    },
    {
      "slot": "2C",
      "equipo": "рџ‡Ірџ‡¦ MARRUECOS"
    },
    {
      "slot": "2K",
      "equipo": ""
    },
    {
      "slot": "2L",
      "equipo": ""
    },
    {
      "slot": "1H",
      "equipo": ""
    },
    {
      "slot": "2J",
      "equipo": ""
    },
    {
      "slot": "1D",
      "equipo": "рџ‡єрџ‡ё ESTADOS UNIDOS"
    },
    {
      "slot": "3 BEFIJ",
      "equipo": ""
    },
    {
      "slot": "1G",
      "equipo": ""
    },
    {
      "slot": "3 AEFHIJ",
      "equipo": ""
    },
    {
      "slot": "1C",
      "equipo": "рџЏґу Ѓ§у Ѓўу Ѓіу ЃЈу Ѓґу Ѓї ESCOCIA"
    },
    {
      "slot": "2F",
      "equipo": ""
    },
    {
      "slot": "2E",
      "equipo": ""
    },
    {
      "slot": "2I",
      "equipo": ""
    },
    {
      "slot": "1A",
      "equipo": "рџ‡Ірџ‡Ѕ MГ‰XICO"
    },
    {
      "slot": "3 CEFHI",
      "equipo": ""
    },
    {
      "slot": "1L",
      "equipo": ""
    },
    {
      "slot": "3 EHIJK",
      "equipo": ""
    },
    {
      "slot": "1J",
      "equipo": ""
    },
    {
      "slot": "2H",
      "equipo": ""
    },
    {
      "slot": "2D",
      "equipo": "рџ‡¦рџ‡є AUSTRALIA"
    },
    {
      "slot": "2G",
      "equipo": ""
    },
    {
      "slot": "1B",
      "equipo": "рџ‡¶рџ‡¦ QATAR"
    },
    {
      "slot": "3 EFGIJ",
      "equipo": ""
    },
    {
      "slot": "1K",
      "equipo": ""
    },
    {
      "slot": "3 DEIJL",
      "equipo": ""
    }
  ],
  "ronda_8avos": [],
  "ronda_cuartos": [],
  "ronda_semifinales": [],
  "finales": {
    "campeon": "",
    "segundo": "",
    "tercero": "",
    "cuarto": ""
  }
}